aqueduct/__init__.py
aqueduct/__main__.py
aqueduct/aqueduct.py
aqueduct/base.py
aqueduct/collector.py
aqueduct/components/__init__.py
aqueduct/components/applets.py
aqueduct/components/applications.py
aqueduct/components/assets.py
aqueduct/components/base.py
aqueduct/components/dashboards.py
aqueduct/components/groups.py
aqueduct/components/keystore.py
aqueduct/components/packages.py
aqueduct/components/plugins.py
aqueduct/components/reports.py
aqueduct/components/roles.py
aqueduct/components/tasks.py
aqueduct/components/users.py
aqueduct/components/workflows.py
aqueduct/components/workspaces.py
aqueduct/data/logging.yml
aqueduct/decorators.py
aqueduct/instance.py
aqueduct/models/__init__.py
aqueduct/models/application.py
aqueduct/models/asset.py
aqueduct/models/base.py
aqueduct/models/dashboard.py
aqueduct/models/fields/__init__.py
aqueduct/models/fields/attachment.py
aqueduct/models/fields/base.py
aqueduct/models/fields/comments.py
aqueduct/models/fields/datetime.py
aqueduct/models/fields/history.py
aqueduct/models/fields/list.py
aqueduct/models/fields/numeric.py
aqueduct/models/fields/reference.py
aqueduct/models/fields/text.py
aqueduct/models/fields/tracking.py
aqueduct/models/fields/usergroup.py
aqueduct/models/fields/valueslist.py
aqueduct/models/group.py
aqueduct/models/package.py
aqueduct/models/plugin.py
aqueduct/models/report.py
aqueduct/models/reports/__init__.py
aqueduct/models/reports/base.py
aqueduct/models/reports/types.py
aqueduct/models/role.py
aqueduct/models/task.py
aqueduct/models/user.py
aqueduct/models/workflow.py
aqueduct/models/workspace.py
aqueduct/utils/__init__.py
aqueduct/utils/differ.py
aqueduct/utils/exceptions.py
aqueduct/utils/logger.py
aqueduct/utils/meta.py
aqueduct/utils/zip.py
sw_aqueduct-2.1.1.dist-info/LICENSE.md
sw_aqueduct-2.1.1.dist-info/WHEEL
sw_aqueduct-2.1.1.dist-info/METADATA
sw_aqueduct-2.1.1.dist-info/RECORD
