Metadata-Version: 2.1
Name: sw-aqueduct
Version: 2.1.1
Summary: A Swimlane content delivery system written in Python
License: MIT
Author: MSAdministrator
Author-email: rickardja@live.com
Requires-Python: >=3.6.2,<4.0.0
Classifier: License :: OSI Approved :: MIT License
Classifier: Programming Language :: Python :: 3
Classifier: Programming Language :: Python :: 3.7
Classifier: Programming Language :: Python :: 3.8
Classifier: Programming Language :: Python :: 3.9
Classifier: Programming Language :: Python :: 3.10
Requires-Dist: attrs (>=21.4.0,<22.0.0)
Requires-Dist: deepdiff (<=5.8.0)
Requires-Dist: fire (>=0.4.0,<0.5.0)
Requires-Dist: packaging (>=21,<22)
Requires-Dist: pendulum (>=2.1.2,<3.0.0)
Requires-Dist: pydantic (>=1.9.1,<2.0.0)
Requires-Dist: pyyaml (>=6.0,<7.0)
Requires-Dist: requests (>=2.27.1,<3.0.0)
